MANIFEST.in
README.rst
setup.py
docs/HISTORY.txt
docs/LICENSE.GPL
docs/LICENSE.txt
docs/images/contact.png
docs/images/contactdirectory.png
ftw/__init__.py
ftw.contacts.egg-info/PKG-INFO
ftw.contacts.egg-info/SOURCES.txt
ftw.contacts.egg-info/dependency_links.txt
ftw.contacts.egg-info/entry_points.txt
ftw.contacts.egg-info/namespace_packages.txt
ftw.contacts.egg-info/not-zip-safe
ftw.contacts.egg-info/requires.txt
ftw.contacts.egg-info/top_level.txt
ftw/contacts/__init__.py
ftw/contacts/adapters.py
ftw/contacts/configure.zcml
ftw/contacts/indexers.py
ftw/contacts/interfaces.py
ftw/contacts/lawgiver.zcml
ftw/contacts/migration.py
ftw/contacts/permissions.zcml
ftw/contacts/resources.zcml
ftw/contacts/testing.py
ftw/contacts/utils.py
ftw/contacts/zipexport.py
ftw/contacts/browser/__init__.py
ftw/contacts/browser/configure.zcml
ftw/contacts/browser/contact.py
ftw/contacts/browser/contactfolder.py
ftw/contacts/browser/vcard.py
ftw/contacts/browser/templates/contact.pt
ftw/contacts/browser/templates/contact_summary.pt
ftw/contacts/browser/templates/contactfolder.pt
ftw/contacts/browser/templates/letters.pt
ftw/contacts/contents/__init__.py
ftw/contacts/contents/contact.py
ftw/contacts/contents/contactfolder.py
ftw/contacts/geo/__init__.py
ftw/contacts/geo/adapters.py
ftw/contacts/geo/configure.zcml
ftw/contacts/geo/profiles/default/metadata.xml
ftw/contacts/geo/profiles/default/types/ftw.contacts.Contact.xml
ftw/contacts/locales/ftw.contacts.pot
ftw/contacts/locales/plone.pot
ftw/contacts/locales/de/LC_MESSAGES/ftw.contacts.po
ftw/contacts/locales/de/LC_MESSAGES/plone.po
ftw/contacts/locales/fr/LC_MESSAGES/ftw.contacts.po
ftw/contacts/locales/fr/LC_MESSAGES/plone.po
ftw/contacts/locales/it/LC_MESSAGES/ftw.contacts.po
ftw/contacts/locales/it/LC_MESSAGES/plone.po
ftw/contacts/profiles/default/actions.xml
ftw/contacts/profiles/default/cssregistry.xml
ftw/contacts/profiles/default/metadata.xml
ftw/contacts/profiles/default/propertiestool.xml
ftw/contacts/profiles/default/registry.xml
ftw/contacts/profiles/default/rolemap.xml
ftw/contacts/profiles/default/types.xml
ftw/contacts/profiles/default/types/ftw.contacts.Contact.xml
ftw/contacts/profiles/default/types/ftw.contacts.ContactFolder.xml
ftw/contacts/profiles/default_plone5/actions.xml
