Metadata-Version: 2.1
Name: ftw.contacts
Version: 1.11.0
Summary: Provides a contact-contenttype
Home-page: https://github.com/4teamwork/ftw.contacts
Author: 4teamwork AG
Author-email: mailto:info@4teamwork.ch
Maintainer: Mathias Leimgruber
License: GPL2
Keywords: ftw plone contacts
Platform: UNKNOWN
Classifier: Framework :: Plone
Classifier: Framework :: Plone :: 4.3
Classifier: Framework :: Plone :: 5.1
Classifier: License :: OSI Approved :: GNU General Public License (GPL)
Classifier: Programming Language :: Python
Classifier: Programming Language :: Python :: 2.7
Classifier: Topic :: Software Development :: Libraries :: Python Modules
Provides-Extra: tests
Provides-Extra: zip_export
Provides-Extra: simplelayout
Provides-Extra: geo
Provides-Extra: ldap
Provides-Extra: plone4
